mkdocs_confluence_plugin/__init__.py
mkdocs_confluence_plugin/plugin.py
mkdocs_confluence_plugin-1.28.0.dist-info/METADATA
mkdocs_confluence_plugin-1.28.0.dist-info/WHEEL
mkdocs_confluence_plugin-1.28.0.dist-info/entry_points.txt
mkdocs_confluence_plugin-1.28.0.dist-info/top_level.txt
mkdocs_confluence_plugin-1.28.0.dist-info/RECORD
