Metadata-Version: 2.4
Name: mkdocs_confluence_plugin
Version: 1.28.0
Summary: MkDocs plugin to export to Confluence
Author-email: Surj Bains <surjit.bains@gmail.com>
Requires-Python: >=3.7
Requires-Dist: pytest==8.0.0
Requires-Dist: pytest-mock==3.12.0
Requires-Dist: coverage==7.5
Requires-Dist: requests
Requires-Dist: pyyaml<7.0,>=6.0
Requires-Dist: mistune
Requires-Dist: md2cf
Requires-Dist: mime
Requires-Dist: pre-commit
Requires-Dist: mkdocs
Requires-Dist: atlassian-python-api
Requires-Dist: Cython
Provides-Extra: dev
Requires-Dist: mkdocs; extra == "dev"
Requires-Dist: pytest; extra == "dev"
Requires-Dist: coverage; extra == "dev"
Requires-Dist: md2cf; extra == "dev"
Requires-Dist: atlassian-python-api; extra == "dev"
Requires-Dist: black; extra == "dev"
